tv_types/__init__.py
tv_types/models.py
tv_types-0.1.0.dist-info/METADATA
tv_types-0.1.0.dist-info/WHEEL
tv_types-0.1.0.dist-info/entry_points.txt
tv_types-0.1.0.dist-info/RECORD
