Metadata-Version: 2.4
Name: tv-types
Version: 0.1.0
Summary: Add your description here
Author-email: Elder Millenial <eldermillenial@protonmail.com>
Requires-Python: >=3.12
Requires-Dist: pydantic>=2.10.4
